dlcli/__init__.py
dlcli/cli.py
dlcli-0.0.1.dist-info/DESCRIPTION.rst
dlcli-0.0.1.dist-info/METADATA
dlcli-0.0.1.dist-info/RECORD
dlcli-0.0.1.dist-info/WHEEL
dlcli-0.0.1.dist-info/entry_points.txt
dlcli-0.0.1.dist-info/metadata.json
dlcli-0.0.1.dist-info/top_level.txt
