Metadata-Version: 2.0
Name: dlcli
Version: 0.0.1
Summary: Command line utility for Dataloop.IO
Home-page: https://github.com/sacreman/dlcli
Author: Steven Acreman
Author-email: steven.acreman@dataloop.io
License: BSD
Platform: any
Classifier: Development Status :: 4 - Beta
Classifier: Environment :: Console
Classifier: Intended Audience :: Developers
Classifier: License :: OSI Approved :: BSD License
Classifier: Operating System :: POSIX
Classifier: Operating System :: MacOS
Classifier: Operating System :: Unix
Classifier: Programming Language :: Python
Classifier: Programming Language :: Python :: 2
Classifier: Programming Language :: Python :: 3
Classifier: Topic :: Software Development :: Libraries :: Python Modules
Requires-Dist: click
